{
	"Version": 3,
	"Parameters": [
		{
			"Id": "PARAM_ANGLE_X",
			"GroupId": "",
			"Name": "角度 X"
		},
		{
			"Id": "PARAM_ANGLE_Y",
			"GroupId": "",
			"Name": "角度 Y"
		},
		{
			"Id": "PARAM_ANGLE_Z",
			"GroupId": "",
			"Name": "角度 Z"
		},
		{
			"Id": "PARAM_EYE_L_OPEN",
			"GroupId": "",
			"Name": "左眼　开闭"
		},
		{
			"Id": "PARAM_EYE_L_SMILE",
			"GroupId": "",
			"Name": "左眼　微笑"
		},
		{
			"Id": "PARAM_EYE_R_OPEN",
			"GroupId": "",
			"Name": "右眼"
		},
		{
			"Id": "PARAM_EYE_R_SMILE",
			"GroupId": "",
			"Name": "右眼　微笑"
		},
		{
			"Id": "PARAM_EYE_BALL_X",
			"GroupId": "",
			"Name": "眼珠 X"
		},
		{
			"Id": "PARAM_EYE_BALL_Y",
			"GroupId": "",
			"Name": "眼珠 Y"
		},
		{
			"Id": "PARAM_BROW_L_Y",
			"GroupId": "",
			"Name": "左眉上下"
		},
		{
			"Id": "PARAM_BROW_R_Y",
			"GroupId": "",
			"Name": "右眉　上下"
		},
		{
			"Id": "PARAM_BROW_L_X",
			"GroupId": "",
			"Name": "左眉　左右"
		},
		{
			"Id": "PARAM_BROW_R_X",
			"GroupId": "",
			"Name": "右眉　左右"
		},
		{
			"Id": "PARAM_BROW_L_ANGLE",
			"GroupId": "",
			"Name": "左眉　角度"
		},
		{
			"Id": "PARAM_BROW_R_ANGLE",
			"GroupId": "",
			"Name": "右眉　角度"
		},
		{
			"Id": "PARAM_BROW_L_FORM",
			"GroupId": "",
			"Name": "左眉　変形"
		},
		{
			"Id": "PARAM_BROW_R_FORM",
			"GroupId": "",
			"Name": "右眉　変形"
		},
		{
			"Id": "PARAM_MOUTH_FORM",
			"GroupId": "",
			"Name": "嘴　变形"
		},
		{
			"Id": "PARAM_MOUTH_OPEN_Y",
			"GroupId": "",
			"Name": "嘴　张开和闭合"
		},
		{
			"Id": "PARAM_CHEEK",
			"GroupId": "",
			"Name": "脸颊泛红"
		},
		{
			"Id": "PARAM_BODY_ANGLE_X",
			"GroupId": "",
			"Name": "身体旋转　X"
		},
		{
			"Id": "PARAM_BODY_ANGLE_Y",
			"GroupId": "",
			"Name": "身体旋转　Y"
		},
		{
			"Id": "PARAM_BODY_ANGLE_Z",
			"GroupId": "",
			"Name": "身体旋转　Z"
		},
		{
			"Id": "PARAM_BREATH",
			"GroupId": "",
			"Name": "呼吸"
		},
		{
			"Id": "PARAM_HAIR_FRONT",
			"GroupId": "",
			"Name": "摇动 前发"
		},
		{
			"Id": "PARAM_HAIR_SIDE",
			"GroupId": "",
			"Name": "摇动 侧发"
		},
		{
			"Id": "PARAM_HAIR_BACK",
			"GroupId": "",
			"Name": "摇动 后发"
		}
	],
	"ParameterGroups": [],
	"Parts": [
		{
			"Id": "PARTS",
			"Name": "資料夾 2"
		},
		{
			"Id": "PARTS_2",
			"Name": "資料夾 1"
		}
	]
}